fdds/__init__.py
fdds/setup_environment.py
fdds/api/__init__.py
fdds/api/api_layer.py
fdds/cli/__init__.py
fdds/cli/command_manager.py
fdds/cli/commands.py
fdds/cli/fdds_cli.py
fdds/config/__init__.py
fdds/config/auto_config.py
fdds/config/config_commands.py
fdds/config/settings.py
fdds/core/__init__.py
fdds/core/concurrency.py
fdds/core/engine.py
fdds/core/migration.py
fdds/core/operation.py
fdds/core/table.py
fdds/core/transaction.py
fdds/core/transaction_commands.py
fdds/fdql/__init__.py
fdds/fdql/commands.py
fdds/fdql/expressions.py
fdds/fdql/fdql_commands.py
fdds/fdql/parser.py
fdds/fdql/query_builder.py
fdds/fdql/stored_procedure.py
fdds/indexing/__init__.py
fdds/indexing/btree.py
fdds/indexing/fulltext.py
fdds/indexing/hashindex.py
fdds/indexing/index_commands.py
fdds/indexing/optimizer.py
fdds/models/__init__.py
fdds/models/base.py
fdds/models/constraints.py
fdds/models/fields.py
fdds/models/triggers.py
fdds/models/views.py
fdds/storage/__init__.py
fdds/storage/backup.py
fdds/storage/backup_commands.py
fdds/storage/file_storage.py
fdds/storage/memory_storage.py
fdds/storage/mmap_storage.py
fdds/storage/mmap_storage_commands.py
fdds/utils/__init__.py
fdds/utils/encryption.py
fdds/utils/encryption_commands.py
fdds/utils/logging.py
fdds/utils/monitoring.py
fdds/utils/validation.py
fdds/utils/validation_commands.py
fdds-0.1.0.dist-info/METADATA
fdds-0.1.0.dist-info/WHEEL
fdds-0.1.0.dist-info/top_level.txt
fdds-0.1.0.dist-info/RECORD
