Metadata-Version: 2.1
Name: fdds
Version: 0.1.0
Summary: Fast Dynamic Database System (FDDS)
Home-page: https://github.com/starrvarse/fdds-software
Author: Arif Hussain
Author-email: starrvarse@gmail.com
Classifier: Programming Language :: Python :: 3
Classifier: License :: OSI Approved :: MIT License
Classifier: Operating System :: OS Independent
Requires-Python: >=3.7
Requires-Dist: Flask==2.3.2
Requires-Dist: cryptography==41.0.3
Requires-Dist: pytest==7.4.0
Requires-Dist: pandas==2.0.3
